crazybin/__init__.py
crazybin/objects.py
crazybin/tiles/__init__.py
crazybin/tiles/frog.json
crazybin/tiles/hex.json
crazybin/tiles/hex_rhomb.json
crazybin/tiles/reptile.json
crazybin-1.0.0.dist-info/METADATA
crazybin-1.0.0.dist-info/WHEEL
crazybin-1.0.0.dist-info/top_level.txt
crazybin-1.0.0.dist-info/RECORD
