Metadata-Version: 2.1
Name: crazybin
Version: 1.0.0
Summary: Much better than hexbins plots! Use any kind of tile to visualize data and pictures!
Author-email: Paul Ockenfuß <paul.ockenfuss@physik.uni-muenchen.de>
Project-URL: Homepage, https://github.com/Ockenfuss/crazybin
Keywords: hexbin,histogram,tiling,parquet,escher
Classifier: Programming Language :: Python
Classifier: Programming Language :: Python :: 3
Classifier: Intended Audience :: Science/Research
Classifier: Intended Audience :: Education
Classifier: Topic :: Multimedia :: Graphics
Classifier: Framework :: Matplotlib
Requires-Python: >=3.9
Requires-Dist: numpy
Requires-Dist: matplotlib
Requires-Dist: shapely
Provides-Extra: dev
Requires-Dist: check-manifest ; extra == 'dev'
Requires-Dist: build ; extra == 'dev'
Requires-Dist: twine ; extra == 'dev'
